un/__init__.py
un-0.0.6.dist-info/licenses/LICENSE
un-0.0.6.dist-info/METADATA
un-0.0.6.dist-info/WHEEL
un-0.0.6.dist-info/top_level.txt
un-0.0.6.dist-info/RECORD
