Metadata-Version: 2.4
Name: un
Version: 0.0.6
Summary: Analyzing classes
Home-page: https://github.com/t-c-w/un
Author: Thor Whalen
License: apache-2.0
Platform: any
License-File: LICENSE
Dynamic: license-file
